LICENSE
README.md
setup.cfg
setup.py
tweetnlp/__init__.py
tweetnlp/loader.py
tweetnlp/util.py
tweetnlp.egg-info/PKG-INFO
tweetnlp.egg-info/SOURCES.txt
tweetnlp.egg-info/dependency_links.txt
tweetnlp.egg-info/entry_points.txt
tweetnlp.egg-info/requires.txt
tweetnlp.egg-info/top_level.txt
tweetnlp/mlm/__init__.py
tweetnlp/mlm/model.py
tweetnlp/ner/__init__.py
tweetnlp/ner/allennlp_crf.py
tweetnlp/ner/dataset.py
tweetnlp/ner/model.py
tweetnlp/ner/trainer.py
tweetnlp/question_answer_generation/__init__.py
tweetnlp/question_answer_generation/dataset.py
tweetnlp/question_answer_generation/model.py
tweetnlp/question_answering/__init__.py
tweetnlp/question_answering/dataset.py
tweetnlp/question_answering/model.py
tweetnlp/sentence_embedding/__init__.py
tweetnlp/sentence_embedding/model.py
tweetnlp/text_classification/__init__.py
tweetnlp/text_classification/dataset.py
tweetnlp/text_classification/model.py
tweetnlp/text_classification/readme_template.py
tweetnlp/text_classification/trainer.py